audio4t/__init__.py
audio4t/common.py
聲音模組/__init__.py
audio4t-0.0.5.dist-info/LICENSE
audio4t-0.0.5.dist-info/METADATA
audio4t-0.0.5.dist-info/WHEEL
audio4t-0.0.5.dist-info/top_level.txt
audio4t-0.0.5.dist-info/RECORD
