Metadata-Version: 2.1
Name: audio4t
Version: 0.0.5
Summary: Audio learning wrapper library for Teenagers
Home-page: https://github.com/beardad1975/audio4t
Author: Wen-Hung, Chang 張文宏
Author-email: beardad1975@nmes.tyc.edu.tw
Platform: Windows
Classifier: Programming Language :: Python :: 3
Classifier: License :: OSI Approved :: MIT License
Classifier: Operating System :: Microsoft :: Windows
Classifier: Natural Language :: Chinese (Traditional)
Requires-Python: >=3.8
License-File: LICENSE
Requires-Dist: pyaudio (==0.2.13)
Requires-Dist: pydub (==0.25.1)
